heizer/VERSION
heizer/__init__.py
heizer/config.py
heizer/env_vars.py
heizer/errors.py
heizer/types.py
heizer/_source/__init__.py
heizer/_source/admin.py
heizer/_source/consumer.py
heizer/_source/enums.py
heizer/_source/message.py
heizer/_source/producer.py
heizer/_source/status_manager.py
heizer/_source/topic.py
heizer/bin/__init__.py
heizer-0.2.0.dist-info/LICENSE
heizer-0.2.0.dist-info/METADATA
heizer-0.2.0.dist-info/WHEEL
heizer-0.2.0.dist-info/top_level.txt
heizer-0.2.0.dist-info/RECORD
