Metadata-Version: 2.1
Name: heizer
Version: 0.2.0
Summary: A python library to easily create kafka producer and consumer
Author-email: Yan Zhang <dev.claude.yan.zhang@gmail.com>
License: MIT License
Project-URL: Homepage, https://github.com/Claudezss/heizer
Project-URL: Bug Tracker, https://github.com/Claudezss/heizer/issues
Keywords: kafka
Classifier: Development Status :: 3 - Alpha
Classifier: Programming Language :: Python :: 3
Classifier: License :: OSI Approved :: MIT License
Classifier: Operating System :: OS Independent
Classifier: Topic :: Software Development :: Libraries
Requires-Python: >=3.7
License-File: LICENSE
Requires-Dist: confluent-kafka
Requires-Dist: typing ; python_version < "3.10"
Requires-Dist: typing-extensions ; python_version < "3.10"
Provides-Extra: dev
Requires-Dist: pre-commit ; extra == 'dev'
Provides-Extra: doc
Requires-Dist: sphinx ; extra == 'doc'
Requires-Dist: sphinx-rtd-theme ; extra == 'doc'
Requires-Dist: myst-parser ; extra == 'doc'
Requires-Dist: wheel ; extra == 'doc'
Requires-Dist: ipython ; extra == 'doc'
Requires-Dist: sphinx-multiversion ; extra == 'doc'
Requires-Dist: requests ; extra == 'doc'
Provides-Extra: socket
Requires-Dist: websockets ; extra == 'socket'
Provides-Extra: test
Requires-Dist: pytest ; extra == 'test'
Requires-Dist: pytest-cov ; extra == 'test'
Requires-Dist: pydantic ; extra == 'test'
